tracmenus/__init__.py
tracmenus/web_ui.py
tracmenus/htdocs/css/tracmenus.css
tracmenus/htdocs/images/arrows-ffffff.png
tracmenus/htdocs/images/shadow.png
tracmenus/htdocs/js/jquery.hoverIntent.js
tracmenus/htdocs/js/superfish.js
tracmenus/htdocs/js/tracmenus.js
TracMenus-0.3.0.dist-info/METADATA
TracMenus-0.3.0.dist-info/WHEEL
TracMenus-0.3.0.dist-info/entry_points.txt
TracMenus-0.3.0.dist-info/top_level.txt
TracMenus-0.3.0.dist-info/RECORD
