Metadata-Version: 2.1
Name: TracMenus
Version: 0.3.0
Summary: Trac Menus
Home-page: https://trac-hacks.org/wiki/MenusPlugin
Author: Catalin Balan
Author-email: cbalan@optaros.com
License: BSD
Platform: UNKNOWN
Classifier: Framework :: Trac
Requires-Dist: Trac
